rpc_differ/__init__.py
rpc_differ/rpc_differ.py
rpc_differ/templates/offline-header.j2
rpc_differ/templates/offline-repo-changes.j2
rpc_differ-0.3.12.dist-info/LICENSE
rpc_differ-0.3.12.dist-info/METADATA
rpc_differ-0.3.12.dist-info/WHEEL
rpc_differ-0.3.12.dist-info/entry_points.txt
rpc_differ-0.3.12.dist-info/top_level.txt
rpc_differ-0.3.12.dist-info/RECORD
